openai_quickstart_python/__init__.py
openai_quickstart_python/app.py
openai_quickstart_python/static/dog.png
openai_quickstart_python/static/main.css
openai_quickstart_python/templates/index.html
openai_quickstart_python-0.4.0.dist-info/LICENSE
openai_quickstart_python-0.4.0.dist-info/METADATA
openai_quickstart_python-0.4.0.dist-info/WHEEL
openai_quickstart_python-0.4.0.dist-info/entry_points.txt
openai_quickstart_python-0.4.0.dist-info/RECORD
